{"status": "done", "action": "Cannot create flow recipe due to incomplete actions", "fallback_action": "Wait until all actions (including Action 3) are marked as completed before attempting to generate a flow recipe.", "persona": "Color Expert", "action_id": 11, "recipe": [{"steps": "Ensure all required actions are fully completed before starting flow recipe creation.", "agent_to_perform_this_action": "Assistant"}, {"steps": "If any required action is not completed, notify and pause until completion is confirmed.", "agent_to_perform_this_action": "Assistant"}], "can_perform_without_user_input": "yes", "scheduled_tasks": [], "metadata": {"user_id": "redacted int"}, "time_took_to_complete": 7.572088241577148}